dataroom/__init__.py
dataroom/core.py
dataroom-1.0.1.dist-info/LICENSE
dataroom-1.0.1.dist-info/METADATA
dataroom-1.0.1.dist-info/WHEEL
dataroom-1.0.1.dist-info/top_level.txt
dataroom-1.0.1.dist-info/RECORD
