Metadata-Version: 2.1
Name: dataroom
Version: 1.0.1
Summary: A powerful and easy-to-use data processing library
Author: Mohammad Taha Gorji
Author-email: MohammadTahaGorjiProfile@gmail.com
Classifier: Programming Language :: Python :: 3
Classifier: License :: OSI Approved :: MIT License
Classifier: Operating System :: OS Independent
Requires-Python: >=3.6
License-File: LICENSE
Requires-Dist: pandas
Requires-Dist: numpy
Requires-Dist: matplotlib
Requires-Dist: seaborn
Requires-Dist: requests
Requires-Dist: sqlalchemy
Requires-Dist: scikit-learn
